odoo8_addon_l10n_br_hr_contract-8.0.0.0.0.99.dev10-py2.7-nspkg.pth
odoo8_addon_l10n_br_hr_contract-8.0.0.0.0.99.dev10.dist-info/METADATA
odoo8_addon_l10n_br_hr_contract-8.0.0.0.0.99.dev10.dist-info/RECORD
odoo8_addon_l10n_br_hr_contract-8.0.0.0.0.99.dev10.dist-info/WHEEL
odoo8_addon_l10n_br_hr_contract-8.0.0.0.0.99.dev10.dist-info/namespace_packages.txt
odoo8_addon_l10n_br_hr_contract-8.0.0.0.0.99.dev10.dist-info/top_level.txt
odoo_addons/l10n_br_hr_contract/README.rst
odoo_addons/l10n_br_hr_contract/__init__.py
odoo_addons/l10n_br_hr_contract/__openerp__.py
odoo_addons/l10n_br_hr_contract/data/l10n_br_hr_contract_data.xml
odoo_addons/l10n_br_hr_contract/data/l10n_br_hr_contract_resignation_data.xml
odoo_addons/l10n_br_hr_contract/i18n/pt_BR.po
odoo_addons/l10n_br_hr_contract/models/__init__.py
odoo_addons/l10n_br_hr_contract/models/hr_contract.py
odoo_addons/l10n_br_hr_contract/security/ir.model.access.csv
odoo_addons/l10n_br_hr_contract/static/description/icon.png
odoo_addons/l10n_br_hr_contract/test/l10n_br_hr_contract_demo.yml
odoo_addons/l10n_br_hr_contract/views/hr_contract_view.xml
